{
  "annotations": {
    "list": [
      {
        "builtIn": 1,
        "datasource": "-- Grafana --",
        "enable": true,
        "hide": true,
        "iconColor": "rgba(0, 211, 255, 1)",
        "name": "Annotations & Alerts",
        "target": {
          "limit": 100,
          "matchAny": false,
          "tags": [],
          "type": "dashboard"
        },
        "type": "dashboard"
      }
    ]
  },
  "editable": true,
  "fiscalYearStartMonth": 0,
  "graphTooltip": 0,
  "id": 2,
  "links": [],
  "liveNow": false,
  "panels": [
    {
      "datasource": {
        "type": "loki",
        "uid": "aq1kAhynk"
      },
      "gridPos": {
        "h": 8,
        "w": 12,
        "x": 0,
        "y": 0
      },
      "id": 4,
      "options": {
        "dedupStrategy": "none",
        "enableLogDetails": true,
        "prettifyLogMessage": false,
        "showCommonLabels": false,
        "showLabels": true,
        "showTime": true,
        "sortOrder": "Descending",
        "wrapLogMessage": true
      },
      "targets": [
        {
          "datasource": {
            "type": "loki",
            "uid": "aq1kAhynk"
          },
          "expr": "{job=\"systemd-journal\"}",
          "refId": "A"
        }
      ],
      "title": "Systemd Log",
      "transformations": [],
      "type": "logs"
    }
  ],
  "refresh": "",
  "schemaVersion": 35,
  "style": "dark",
  "tags": [],
  "templating": {
    "list": []
  },
  "time": {
    "from": "now-6h",
    "to": "now"
  },
  "timepicker": {},
  "timezone": "",
  "title": "Logs",
  "uid": "mB6K0hs7k",
  "version": 5,
  "weekStart": ""
}
